vba_precompiler/__init__.py
vba_precompiler/__main__.py
vba_precompiler/compiler.py
vba_precompiler/precompiler_visitor.py
vba_precompiler-0.0.1.dist-info/LICENSE
vba_precompiler-0.0.1.dist-info/METADATA
vba_precompiler-0.0.1.dist-info/WHEEL
vba_precompiler-0.0.1.dist-info/top_level.txt
vba_precompiler-0.0.1.dist-info/RECORD
