Metadata-Version: 2.1
Name: vba_precompiler
Version: 0.0.1
Summary: Precompile VBA code.
Author-email: Kevin Nowaczyk <beakerboy99@yahoo.com>
Project-URL: Homepage, https://github.com/Beakerboy/VBA-Precompiler
Project-URL: Bug Tracker, https://github.com/Beakerboy/VBA-Precompiler/issues
Classifier: Programming Language :: Python :: 3
Classifier: License :: OSI Approved :: MIT License
Classifier: Operating System :: OS Independent
Requires-Python: >=3.7
License-File: LICENSE
Requires-Dist: antlr4-python3-runtime
Requires-Dist: antlr4-tools
Requires-Dist: antlr4-vba
Requires-Dist: python-dateutil
Provides-Extra: tests
Requires-Dist: coveralls ; extra == 'tests'
Requires-Dist: flake8-annotations ; extra == 'tests'
Requires-Dist: mypy ; extra == 'tests'
Requires-Dist: pep8-naming ; extra == 'tests'
Requires-Dist: pytest ; extra == 'tests'
Requires-Dist: pytest-cov ; extra == 'tests'
Requires-Dist: pytest-mock ; extra == 'tests'
Requires-Dist: types-antlr4-python3-runtime ; extra == 'tests'
Requires-Dist: types-python-dateutil ; extra == 'tests'
